sysfetch_win/__init__.py
sysfetch_win/argpar.py
sysfetch_win/art.py
sysfetch_win/main.py
sysfetch_win/sysfetch.py
sysfetch_win-0.9.dist-info/LICENSE
sysfetch_win-0.9.dist-info/METADATA
sysfetch_win-0.9.dist-info/WHEEL
sysfetch_win-0.9.dist-info/entry_points.txt
sysfetch_win-0.9.dist-info/top_level.txt
sysfetch_win-0.9.dist-info/RECORD
