Metadata-Version: 2.1
Name: sysfetch-win
Version: 0.9
Summary: Fetch Info About Your Windows System
Home-page: https://github.com/nandydark/sysfetch-win
Author: NandyDark
License: MIT Licence
Keywords: sysfetch,sysfetch-win,nandydark,neofetch,neofetch-win
Platform: UNKNOWN
Requires-Dist: colorama
Requires-Dist: psutil
